fastly/__init__.py
fastly/api_client.py
fastly/configuration.py
fastly/exceptions.py
fastly/model_utils.py
fastly/rest.py
fastly/api/__init__.py
fastly/api/acl_api.py
fastly/api/acl_entry_api.py
fastly/api/acls_in_compute_api.py
fastly/api/apex_redirect_api.py
fastly/api/automation_tokens_api.py
fastly/api/backend_api.py
fastly/api/billing_address_api.py
fastly/api/billing_invoices_api.py
fastly/api/billing_usage_metrics_api.py
fastly/api/cache_settings_api.py
fastly/api/condition_api.py
fastly/api/config_store_api.py
fastly/api/config_store_item_api.py
fastly/api/contact_api.py
fastly/api/content_api.py
fastly/api/customer_addresses_api.py
fastly/api/customer_api.py
fastly/api/ddos_protection_api.py
fastly/api/dictionary_api.py
fastly/api/dictionary_info_api.py
fastly/api/dictionary_item_api.py
fastly/api/diff_api.py
fastly/api/director_api.py
fastly/api/director_backend_api.py
fastly/api/dm_domains_api.py
fastly/api/domain_api.py
fastly/api/domain_inspector_historical_api.py
fastly/api/domain_inspector_realtime_api.py
fastly/api/domain_ownerships_api.py
fastly/api/domain_research_api.py
fastly/api/events_api.py
fastly/api/gzip_api.py
fastly/api/header_api.py
fastly/api/healthcheck_api.py
fastly/api/historical_api.py
fastly/api/http3_api.py
fastly/api/iam_permissions_api.py
fastly/api/iam_roles_api.py
fastly/api/iam_service_groups_api.py
fastly/api/iam_user_groups_api.py
fastly/api/image_optimizer_default_settings_api.py
fastly/api/insights_api.py
fastly/api/invitations_api.py
fastly/api/kv_store_api.py
fastly/api/kv_store_item_api.py
fastly/api/log_explorer_api.py
fastly/api/logging_azureblob_api.py
fastly/api/logging_bigquery_api.py
fastly/api/logging_cloudfiles_api.py
fastly/api/logging_datadog_api.py
fastly/api/logging_digitalocean_api.py
fastly/api/logging_elasticsearch_api.py
fastly/api/logging_ftp_api.py
fastly/api/logging_gcs_api.py
fastly/api/logging_grafanacloudlogs_api.py
fastly/api/logging_heroku_api.py
fastly/api/logging_honeycomb_api.py
fastly-12.1.0.dist-info/METADATA
fastly-12.1.0.dist-info/WHEEL
fastly-12.1.0.dist-info/licenses/LICENSE
fastly-12.1.0.dist-info/RECORD
