Metadata-Version: 2.4
Name: fastly
Version: 12.1.0
Summary: A Python Fastly API client library
Project-URL: Homepage, https://github.com/fastly/fastly-py
Project-URL: Bug Tracker, https://github.com/fastly/fastly-py/issues
Author-email: Fastly <oss@fastly.com>
License-File: LICENSE
Classifier: License :: OSI Approved :: MIT License
Classifier: Operating System :: OS Independent
Classifier: Programming Language :: Python :: 3
Requires-Python: >=3.6
Requires-Dist: python-dateutil
Requires-Dist: urllib3>=1.25.3
